wssx126/__init__.py
wssx126/sx1268.py
wssx126-0.0.5.dist-info/LICENSE
wssx126-0.0.5.dist-info/METADATA
wssx126-0.0.5.dist-info/WHEEL
wssx126-0.0.5.dist-info/top_level.txt
wssx126-0.0.5.dist-info/RECORD
