Metadata-Version: 2.1
Name: wssx126
Version: 0.0.5
Summary: Simple controller for waveshare raspberry hats based on sx126 radio transceivers
Home-page: https://github.com/Vermibus/raspberry-waveshare-sx126X-controller
Author: Mateusz Grefka
Author-email: grefkamateusz@gmail.com
License: UNKNOWN
Project-URL: Bug Tracker, https://github.com/Vermibus/raspberry-waveshare-sx126X-controller/issues
Platform: UNKNOWN
Classifier: Programming Language :: Python :: 3
Classifier: License :: OSI Approved :: MIT License
Classifier: Operating System :: OS Independent
Requires-Python: >=3.6
License-File: LICENSE
